app/__init__.py
app/main.py
app/api/__init__.py
app/api/main.py
app/api/routes/accounts.py
app/api/routes/claude.py
app/api/routes/settings.py
app/api/routes/statistics.py
app/core/__init__.py
app/core/account.py
app/core/claude_session.py
app/core/config.py
app/core/error_handler.py
app/core/exceptions.py
app/core/http_client.py
app/core/static.py
app/core/external/claude_client.py
app/dependencies/__init__.py
app/dependencies/auth.py
app/locales/en.json
app/locales/zh.json
app/models/__init__.py
app/models/claude.py
app/models/internal.py
app/models/streaming.py
app/processors/__init__.py
app/processors/base.py
app/processors/pipeline.py
app/processors/claude_ai/__init__.py
app/processors/claude_ai/claude_api_processor.py
app/processors/claude_ai/claude_web_processor.py
app/processors/claude_ai/context.py
app/processors/claude_ai/event_parser_processor.py
app/processors/claude_ai/message_collector_processor.py
app/processors/claude_ai/model_injector_processor.py
app/processors/claude_ai/non_streaming_response_processor.py
app/processors/claude_ai/pipeline.py
app/processors/claude_ai/stop_sequences_processor.py
app/processors/claude_ai/streaming_response_processor.py
app/processors/claude_ai/tavern_test_message_processor.py
app/processors/claude_ai/token_counter_processor.py
app/processors/claude_ai/tool_call_event_processor.py
app/processors/claude_ai/tool_result_processor.py
app/services/__init__.py
app/services/account.py
app/services/cache.py
app/services/i18n.py
app/services/oauth.py
app/services/session.py
app/services/tool_call.py
app/services/event_processing/__init__.py
app/services/event_processing/event_parser.py
app/services/event_processing/event_serializer.py
app/utils/__init__.py
app/utils/logger.py
app/utils/messages.py
app/utils/retry.py
app/locales/en.json
app/locales/zh.json
app/static/index.html
app/static/vite.svg
app/static/assets/index-C-_oh9s7.css
app/static/assets/index-DhB3XcXo.js
clove_proxy-0.3.1.dist-info/METADATA
clove_proxy-0.3.1.dist-info/WHEEL
clove_proxy-0.3.1.dist-info/entry_points.txt
clove_proxy-0.3.1.dist-info/licenses/LICENSE
clove_proxy-0.3.1.dist-info/RECORD
