Metadata-Version: 2.4
Name: clove-proxy
Version: 0.3.1
Summary: A Claude.ai reverse proxy
Project-URL: Homepage, https://github.com/mirrorange/clove
Project-URL: Bug Tracker, https://github.com/mirrorange/clove/issues
Project-URL: Documentation, https://github.com/mirrorange/clove#readme
Author-email: mirrorange <orange@freesia.ink>
License: MIT
License-File: LICENSE
Keywords: ai,claude,fastapi,proxy
Classifier: Development Status :: 4 - Beta
Classifier: Intended Audience :: Education
Classifier: License :: OSI Approved :: MIT License
Classifier: Programming Language :: Python :: 3
Classifier: Programming Language :: Python :: 3.11
Classifier: Programming Language :: Python :: 3.12
Classifier: Programming Language :: Python :: 3.13
Classifier: Topic :: Software Development :: Libraries :: Python Modules
Requires-Python: >=3.11
Requires-Dist: fastapi>=0.115.14
Requires-Dist: httpx>=0.28.1
Requires-Dist: json5>=0.12.0
Requires-Dist: loguru>=0.7.3
Requires-Dist: pydantic-settings>=2.10.1
Requires-Dist: pydantic>=2.11.7
Requires-Dist: tenacity>=9.1.2
Requires-Dist: tiktoken>=0.9.0
Requires-Dist: uvicorn>=0.35.0
Provides-Extra: curl
Requires-Dist: curl-cffi>=0.11.4; extra == 'curl'
Provides-Extra: dev
Requires-Dist: build>=1.0.0; extra == 'dev'
Requires-Dist: ruff>=0.12.2; extra == 'dev'
Provides-Extra: rnet
Requires-Dist: rnet>=2.3.9; extra == 'rnet'
